davinciutils/__init__.py
davinciutils/prompt.py
gptutils/__init__.py
gptutils/prompt.py
davinciutils-0.1.1.dist-info/METADATA
davinciutils-0.1.1.dist-info/WHEEL
davinciutils-0.1.1.dist-info/top_level.txt
davinciutils-0.1.1.dist-info/RECORD
