Metadata-Version: 2.1
Name: davinciutils
Version: 0.1.1
Summary: A package that contains utility functions to call OpenAI davinci APIs
Home-page: UNKNOWN
Author: UNKNOWN
Author-email: UNKNOWN
License: UNKNOWN
Platform: UNKNOWN
